preprocess1/__init__.py
preprocess1/toolkit.py
preprocess1-0.1.42.dist-info/LICENSE
preprocess1-0.1.42.dist-info/METADATA
preprocess1-0.1.42.dist-info/WHEEL
preprocess1-0.1.42.dist-info/top_level.txt
preprocess1-0.1.42.dist-info/RECORD
