Metadata-Version: 2.1
Name: preprocess1
Version: 0.1.42
Summary: UNKNOWN
Home-page: https://github.com/mfahadakbar
Author: Fahad Akbar
Author-email: fahad.akbar@gmail.com
License: UNKNOWN
Platform: UNKNOWN
Requires-Dist: scikit-learn
Requires-Dist: datetime
Requires-Dist: pandas
Requires-Dist: numpy
Requires-Dist: ipywidgets
Requires-Dist: IPython
Requires-Dist: scipy
Requires-Dist: datefinder
Requires-Dist: pyod
Requires-Dist: lightgbm
